kriegspiel/__init__.py
kriegspiel/berkeley.py
kriegspiel/move.py
kriegspiel-1.1.1.dist-info/LICENSE
kriegspiel-1.1.1.dist-info/METADATA
kriegspiel-1.1.1.dist-info/WHEEL
kriegspiel-1.1.1.dist-info/top_level.txt
kriegspiel-1.1.1.dist-info/RECORD
