Metadata-Version: 2.1
Name: kriegspiel
Version: 1.1.1
Summary: Python Kriegspiel Game
Author-email: Fil <alexander@kriegspiel.org>
Project-URL: Homepage, https://github.com/Kriegspiel/ks-game/
Project-URL: Bug Tracker, https://github.com/Kriegspiel/ks-game/issues
Classifier: Programming Language :: Python :: 3
Classifier: License :: OSI Approved :: MIT License
Classifier: Operating System :: OS Independent
Classifier: Intended Audience :: Science/Research
Classifier: Topic :: Games/Entertainment
Classifier: Operating System :: OS Independent
Requires-Python: >=3.7
License-File: LICENSE
